mqtt_docker_controller/__init__.py
mqtt_docker_controller/__main__.py
mqtt_docker_controller/broker.py
mqtt_docker_controller/cli.py
mqtt_docker_controller/client.py
mqtt_docker_controller/config.py
mqtt_docker_controller-0.1.6.dist-info/licenses/LICENSE
mqtt_docker_controller-0.1.6.dist-info/METADATA
mqtt_docker_controller-0.1.6.dist-info/WHEEL
mqtt_docker_controller-0.1.6.dist-info/entry_points.txt
mqtt_docker_controller-0.1.6.dist-info/top_level.txt
mqtt_docker_controller-0.1.6.dist-info/RECORD
