Metadata-Version: 2.4
Name: mqtt-docker-controller
Version: 0.1.6
Summary: A comprehensive and handy MQTT and Docker broker management tool
Author-email: Dylan Wall <dylan@someemail.com>
License: MIT
Project-URL: Homepage, https://github.com/DylanWall96/mqtt-docker-controller
Project-URL: Bug Reports, https://github.com/DylanWall96/mqtt-docker-controller/issues
Project-URL: Source, https://github.com/DylanWall96/mqtt-docker-controller/
Keywords: mqtt,docker,broker,iot,messaging,controller,automation
Classifier: Development Status :: 3 - Alpha
Classifier: Intended Audience :: Developers
Classifier: Topic :: Software Development :: Build Tools
Classifier: Topic :: Communications
Classifier: Topic :: Internet :: WWW/HTTP
Classifier: Topic :: Software Development :: Libraries :: Python Modules
Classifier: License :: OSI Approved :: MIT License
Classifier: Programming Language :: Python :: 3
Classifier: Programming Language :: Python :: 3.8
Classifier: Programming Language :: Python :: 3.9
Classifier: Programming Language :: Python :: 3.10
Classifier: Programming Language :: Python :: 3.11
Classifier: Programming Language :: Python :: 3 :: Only
Requires-Python: >=3.8
License-File: LICENSE
Requires-Dist: paho-mqtt>=1.6.1
Requires-Dist: docker>=6.1.0
Provides-Extra: dev
Requires-Dist: check-manifest; extra == "dev"
Requires-Dist: pytest; extra == "dev"
Requires-Dist: pytest-cov; extra == "dev"
Requires-Dist: flake8; extra == "dev"
Requires-Dist: black; extra == "dev"
Requires-Dist: mypy; extra == "dev"
Provides-Extra: test
Requires-Dist: pytest; extra == "test"
Requires-Dist: pytest-cov; extra == "test"
Dynamic: license-file
